MANIFEST.in
pyproject.toml
requirements.txt
setup.py
cra5/registry.py
cra5/version.py
cra5.egg-info/PKG-INFO
cra5.egg-info/SOURCES.txt
cra5.egg-info/dependency_links.txt
cra5.egg-info/not-zip-safe
cra5.egg-info/requires.txt
cra5.egg-info/top_level.txt
cra5/__pycache__/registry.cpython-310.pyc
cra5/api/__init__.py
cra5/api/cra5_268v_config.py
cra5/api/cra5_api.py
cra5/api/era5_config.py
cra5/api/era5_downloader.py
cra5/api/mean_std.json
cra5/api/mean_std_single.json
cra5/api/utils.py
cra5/api/__pycache__/__init__.cpython-310.pyc
cra5/api/__pycache__/cra5_api.cpython-310.pyc
cra5/api/__pycache__/utils.cpython-310.pyc
cra5/dataset/cra5_base.py
cra5/dataset/era5_base_nc.py
cra5/dataset/era5_base_npy.py
cra5/dataset/mean_std.json
cra5/dataset/mean_std_single.json
cra5/dataset/__pycache__/era5_downloader.cpython-310.pyc
cra5/models/compressai/__init__.py
cra5/models/compressai/__pycache__/__init__.cpython-310.pyc
cra5/models/compressai/cpp_exts/ops/ops.cpp
cra5/models/compressai/cpp_exts/rans/rans_interface.cpp
cra5/models/compressai/cpp_exts/rans/rans_interface.hpp
cra5/models/compressai/datasets/__init__.py
cra5/models/compressai/datasets/image.py
cra5/models/compressai/datasets/pregenerated.py
cra5/models/compressai/datasets/rawvideo.py
cra5/models/compressai/datasets/video.py
cra5/models/compressai/datasets/vimeo90k.py
cra5/models/compressai/datasets/__pycache__/__init__.cpython-310.pyc
cra5/models/compressai/datasets/__pycache__/image.cpython-310.pyc
cra5/models/compressai/datasets/__pycache__/pregenerated.cpython-310.pyc
cra5/models/compressai/datasets/__pycache__/rawvideo.cpython-310.pyc
cra5/models/compressai/datasets/__pycache__/video.cpython-310.pyc
cra5/models/compressai/datasets/__pycache__/vimeo90k.cpython-310.pyc
cra5/models/compressai/entropy_models/__init__.py
cra5/models/compressai/entropy_models/entropy_models.py
cra5/models/compressai/entropy_models/__pycache__/__init__.cpython-310.pyc
cra5/models/compressai/entropy_models/__pycache__/entropy_models.cpython-310.pyc
cra5/models/compressai/jpeg/calculate_mse.py
cra5/models/compressai/jpeg/int16.py
cra5/models/compressai/latent_codecs/__init__.py
