Metadata-Version: 2.1
Name: cra5
Version: 0.0.3.dev1
Summary: A large compression model for weather and climate data, which compresses a 200+ TB ERA5 dataset into a new 0.7TB CRA5 dataset.
Home-page: https://github.com/taohan10200/CRA5
Author: HAN Tao
Author-email: hantao10200@gmail.com
License: BSD 3-Clause Clear License
Classifier: Development Status :: 3 - Alpha
Classifier: Intended Audience :: Developers
Classifier: Intended Audience :: Science/Research
Classifier: License :: OSI Approved :: BSD License
Classifier: Programming Language :: Python :: 3.8
Classifier: Programming Language :: Python :: 3.9
Classifier: Programming Language :: Python :: 3.10
Classifier: Topic :: Scientific/Engineering :: Artificial Intelligence
Requires-Python: >=3.8
Requires-Dist: einops
Requires-Dist: numpy>=1.21.0
Requires-Dist: pandas
Requires-Dist: scipy
Requires-Dist: matplotlib
Requires-Dist: torch<2.3,>=1.7.1
Requires-Dist: torch-geometric>=2.3.0
Requires-Dist: typing-extensions>=4.0.0
Requires-Dist: torchvision
Requires-Dist: pytorch-msssim
Requires-Dist: tqdm
Provides-Extra: test
Requires-Dist: pytest; extra == "test"
Requires-Dist: pytest-cov; extra == "test"
Requires-Dist: plotly; extra == "test"
Provides-Extra: dev
Requires-Dist: pytest; extra == "dev"
Requires-Dist: pytest-cov; extra == "dev"
Requires-Dist: plotly; extra == "dev"
Requires-Dist: black; extra == "dev"
Requires-Dist: flake8; extra == "dev"
Requires-Dist: flake8-bugbear; extra == "dev"
Requires-Dist: flake8-comprehensions; extra == "dev"
Requires-Dist: isort; extra == "dev"
Requires-Dist: mypy; extra == "dev"
Provides-Extra: doc
Requires-Dist: sphinx; extra == "doc"
Requires-Dist: sphinx-book-theme; extra == "doc"
Requires-Dist: Jinja2<3.1; extra == "doc"
Provides-Extra: tutorials
Requires-Dist: jupyter; extra == "tutorials"
Requires-Dist: ipywidgets; extra == "tutorials"
Provides-Extra: pointcloud
Requires-Dist: pointops-yoda; extra == "pointcloud"
Requires-Dist: pyntcloud-yoda; extra == "pointcloud"
Provides-Extra: all
Requires-Dist: jupyter; extra == "all"
Requires-Dist: pyntcloud-yoda; extra == "all"
Requires-Dist: isort; extra == "all"
Requires-Dist: plotly; extra == "all"
Requires-Dist: sphinx; extra == "all"
Requires-Dist: Jinja2<3.1; extra == "all"
Requires-Dist: ipywidgets; extra == "all"
Requires-Dist: pytest-cov; extra == "all"
Requires-Dist: flake8-comprehensions; extra == "all"
Requires-Dist: black; extra == "all"
Requires-Dist: pytest; extra == "all"
Requires-Dist: flake8-bugbear; extra == "all"
Requires-Dist: sphinx-book-theme; extra == "all"
Requires-Dist: pointops-yoda; extra == "all"
Requires-Dist: mypy; extra == "all"
Requires-Dist: flake8; extra == "all"
